tajimas_d/__init__.py
tajimas_d/_tajimas_d.py
tajimas_d-2.0.4.dist-info/licenses/LICENSE
tajimas_d-2.0.4.dist-info/METADATA
tajimas_d-2.0.4.dist-info/WHEEL
tajimas_d-2.0.4.dist-info/entry_points.txt
tajimas_d-2.0.4.dist-info/top_level.txt
tajimas_d-2.0.4.dist-info/RECORD
