Metadata-Version: 2.4
Name: tajimas_d
Version: 2.0.4
Summary: Computes Tajimas D, the Pi- or Watterson-Estimator for multiple sequences.
Home-page: https://github.com/not-a-feature/tajimas_d/
Author: Jules Kreuer / not_a_feature
License: gpl-3.0
Keywords: Tajima,Tajimas D,Pi,Watterson,Estimator,Population,Bioinformatics,Genetics
Platform: unix
Platform: linux
Platform: osx
Platform: cygwin
Platform: win32
Classifier: Programming Language :: Python :: 3
Requires-Python: >=3.8
License-File: LICENSE
Requires-Dist: miniFasta>=2.2
Provides-Extra: testing
Requires-Dist: pytest>=6.0; extra == "testing"
Requires-Dist: pytest-cov>=2.0; extra == "testing"
Requires-Dist: tox>=3.20; extra == "testing"
Requires-Dist: miniFasta>=2.2; extra == "testing"
Dynamic: license-file
